sec/__init__.py
sec/__main__.py
sec/util.py
sec/cli/__init__.py
sec/function/__init__.py
sec/function/cli.py
sec/function/client/__init__.py
sec/function/client/base.py
sec/function/client/queue.py
sec/function/client/repo.py
sec/function/client/task.py
sec/function/client/template.py
sec/mattermost/__init__.py
sec/mongo/__init__.py
ssdk-0.0.3.dist-info/METADATA
ssdk-0.0.3.dist-info/WHEEL
ssdk-0.0.3.dist-info/entry_points.txt
ssdk-0.0.3.dist-info/top_level.txt
ssdk-0.0.3.dist-info/RECORD
