Metadata-Version: 2.1
Name: ssdk
Version: 0.0.3
Summary: UNKNOWN
Home-page: UNKNOWN
Author: 
Author-email: 
License: UNKNOWN
Platform: UNKNOWN
Classifier: Programming Language :: Python :: 3
Classifier: License :: OSI Approved :: MIT License
Classifier: Operating System :: OS Independent
Requires-Python: >=3.6
Requires-Dist: fire (==0.3.1)
Requires-Dist: pymongo (==3.11.2)
Requires-Dist: requests (==2.25.1)
Requires-Dist: tabulate (==0.8.7)
Requires-Dist: PyYAML (==5.4.1)
